.gitignore
.gitlab-ci.yml
LICENSE
MANIFEST.in
README.md
setup.cfg
setup.py
docker/Dockerfile
docker/build-container.sh
probator/__init__.py
probator/app.py
probator/cli.py
probator/config.py
probator/constants.py
probator/database.py
probator/exceptions.py
probator/json_utils.py
probator/log.py
probator/utils.py
probator/wrappers.py
probator/wsgi.py
probator.egg-info/PKG-INFO
probator.egg-info/SOURCES.txt
probator.egg-info/dependency_links.txt
probator.egg-info/entry_points.txt
probator.egg-info/not-zip-safe
probator.egg-info/requires.txt
probator.egg-info/top_level.txt
probator/data/migrations/README
probator/data/migrations/alembic.ini
probator/data/migrations/env.py
probator/data/migrations/script.py.mako
probator/data/migrations/versions/345a41c69ba1_adding_base_resource_attributes.py
probator/data/migrations/versions/397dcb772234_initial_schema.py
probator/data/migrations/versions/4223d2b4b66b_adding_name_and_email_to_users.py
probator/data/migrations/versions/54438c2b1535_adding_api_key_models.py
probator/data/migrations/versions/8a9532dbe303_adding_base_attributes_to_issues.py
probator/data/migrations/versions/8fef9c67eb44_update_dns_resource_names.py
probator/data/migrations/versions/add1e10105f5_adding_account_location_to_issues.py
probator/data/migrations/versions/f982eb32021d_fix_password_field_length.py
probator/data/templates/cloudtrail_s3_bucket_policy.json
probator/data/templates/cloudtrail_sns_policy.json
probator/data/templates/domain_hijacking.html
probator/data/templates/domain_hijacking.txt
probator/data/templates/required_tags_notice.html
probator/data/templates/required_tags_notice.txt
probator/data/templates/syslog_format.json
probator/data/templates/unattached_ebs_volume.html
probator/data/templates/unattached_ebs_volume.txt
probator/data/templates/vpc_flow_logs_iam_role_trust.json
probator/data/templates/vpc_flow_logs_role_policy.json
probator/plugins/__init__.py
probator/plugins/auth/__init__.py
probator/plugins/auth/api.py
probator/plugins/auth/local.py
probator/plugins/collectors/__init__.py
probator/plugins/collectors/aws/__init__.py
probator/plugins/collectors/aws/account.py
probator/plugins/collectors/aws/region.py
probator/plugins/commands/__init__.py
